[
  {
    "nome": "Renato Vieira",
    "data_nascimento": "1989-11-11",
    "endereco": {
      "logradouro": "Avenida Central",
      "numero": "500",
      "bairro": "Centro Norte",
      "cidade": "São Paulo",
      "estado": "SP",
      "CEP": "345123-876"
    },
    "contato": {
      "telefone": "115678234",
      "email": "renato.vieira@gmail.com"
    },
    "subcontato01": {
      "telefone": "1192345678",
      "whatssapp": true
    },
    "convenio": {
      "nome": "Amil Saúde",
      "validade": "2026-07-25",
      "CNPJ": "23456178907",
      "carencia": 20
    },
    "documentos": {
      "CPF": "23456789012",
      "RG": "SP234561",
      "SUS": "48927394589372"
    }
  }
]